{
    "allEntities": [
        {
            "label": "state", 
            "offsets": [
                {
                    "length": 5, 
                    "offset": 12
                }
            ], 
            "types": [
                {
                    "label": "Thing", 
                    "uri": "http://www.w3.org/2002/07/owl#Thing"
                }, 
                {
                    "label": "non abducible collection", 
                    "uri": "http://sw.opencyc.org/2008/06/10/concept/Mx4roVp5xVzKEdiLrQAH6RYvVA"
                }, 
                {
                    "label": "government organizations organization topic", 
                    "uri": "http://sw.opencyc.org/2008/06/10/concept/Mx4r8sgDFmJsQdiZTqJodntKpA"
                }, 
                {
                    "label": "type of geographical entity classified by hierarchy", 
                    "uri": "http://sw.opencyc.org/2008/06/10/concept/Mx4rv-FNbpwpEbGdrcN5Y29ycA"
                }, 
                {
                    "label": "terrorism-topic", 
                    "uri": "http://sw.opencyc.org/2008/06/10/concept/Mx4rSuNLCPsCEdmAAAACs6hcqg"
                }, 
                {
                    "label": "type of object", 
                    "uri": "http://sw.opencyc.org/2008/06/10/concept/Mx4rvWXYgJwpEbGdrcN5Y29ycA"
                }, 
                {
                    "label": "spatially disjoint object type", 
                    "uri": "http://sw.opencyc.org/2008/06/10/concept/Mx4rpPHhAOB1EdqAAAACs6hRXg"
                }, 
                {
                    "label": "geopolitical entities geography topic", 
                    "uri": "http://sw.opencyc.org/2008/06/10/concept/Mx4r8iXRcmJsQdiaQpTHoJEKKA"
                }
            ], 
            "uri": "http://dbpedia.org/resource/State"
        }, 
        {
            "label": "Texas", 
            "offsets": [
                {
                    "length": 5, 
                    "offset": 58
                }
            ], 
            "types": [
                {
                    "label": "Place", 
                    "uri": "http://dbpedia.org/ontology/Place"
                }, 
                {
                    "label": "Resource", 
                    "uri": "http://www.w3.org/2000/01/rdf-schema#Resource"
                }, 
                {
                    "label": "States Of The Confederate States Of America", 
                    "uri": "http://dbpedia.org/class/yago/StatesOfTheConfederateStatesOfAmerica"
                }, 
                {
                    "label": "Yago Geo Entity", 
                    "uri": "http://dbpedia.org/class/yago/YagoGeoEntity"
                }, 
                {
                    "label": "States And Territories Established In1845", 
                    "uri": "http://dbpedia.org/class/yago/StatesAndTerritoriesEstablishedIn1845"
                }, 
                {
                    "label": "Class", 
                    "uri": "http://www.w3.org/2002/07/owl#Class"
                }, 
                {
                    "label": "Populated Place", 
                    "uri": "http://dbpedia.org/ontology/PopulatedPlace"
                }, 
                {
                    "label": "Thing", 
                    "uri": "http://www.w3.org/2002/07/owl#Thing"
                }, 
                {
                    "label": "nationality", 
                    "uri": "http://sw.opencyc.org/2008/06/10/concept/en/PersonTypeByNationality"
                }, 
                {
                    "label": "States Of The United States", 
                    "uri": "http://dbpedia.org/class/yago/StatesOfTheUnitedStates"
                }, 
                {
                    "label": "Locations", 
                    "uri": "http://dbpedia.org/class/yago/Locations"
                }, 
                {
                    "label": " Feature", 
                    "uri": "http://www.opengis.net/gml/_Feature"
                }, 
                {
                    "label": "Administrative Region", 
                    "uri": "http://dbpedia.org/ontology/AdministrativeRegion"
                }
            ], 
            "uri": "http://dbpedia.org/resource/Texas"
        }, 
        {
            "label": "Childress", 
            "offsets": [
                {
                    "length": 9, 
                    "offset": 103
                }
            ], 
            "types": [
                {
                    "label": "Thing", 
                    "uri": "http://www.w3.org/2002/07/owl#Thing"
                }, 
                {
                    "label": "Resource", 
                    "uri": "http://www.w3.org/2000/01/rdf-schema#Resource"
                }
            ], 
            "uri": "http://dbpedia.org/resource/Childress"
        }
    ], 
    "articleUrl": "http://www.nytimes.com/2013/02/26/us/strong-storm-in-plains-brings-added-hazards.html?ref=us", 
    "category": "us", 
    "docID": "S-0353", 
    "elementNumber": 22, 
    "mainEntities": [
        {
            "label": "state", 
            "offsets": [
                {
                    "length": 5, 
                    "offset": 12
                }
            ], 
            "types": [
                {
                    "label": "Thing", 
                    "uri": "http://www.w3.org/2002/07/owl#Thing"
                }, 
                {
                    "label": "non abducible collection", 
                    "uri": "http://sw.opencyc.org/2008/06/10/concept/Mx4roVp5xVzKEdiLrQAH6RYvVA"
                }, 
                {
                    "label": "government organizations organization topic", 
                    "uri": "http://sw.opencyc.org/2008/06/10/concept/Mx4r8sgDFmJsQdiZTqJodntKpA"
                }, 
                {
                    "label": "type of geographical entity classified by hierarchy", 
                    "uri": "http://sw.opencyc.org/2008/06/10/concept/Mx4rv-FNbpwpEbGdrcN5Y29ycA"
                }, 
                {
                    "label": "terrorism-topic", 
                    "uri": "http://sw.opencyc.org/2008/06/10/concept/Mx4rSuNLCPsCEdmAAAACs6hcqg"
                }, 
                {
                    "label": "type of object", 
                    "uri": "http://sw.opencyc.org/2008/06/10/concept/Mx4rvWXYgJwpEbGdrcN5Y29ycA"
                }, 
                {
                    "label": "spatially disjoint object type", 
                    "uri": "http://sw.opencyc.org/2008/06/10/concept/Mx4rpPHhAOB1EdqAAAACs6hRXg"
                }, 
                {
                    "label": "geopolitical entities geography topic", 
                    "uri": "http://sw.opencyc.org/2008/06/10/concept/Mx4r8iXRcmJsQdiaQpTHoJEKKA"
                }
            ], 
            "uri": "http://dbpedia.org/resource/State"
        }, 
        {
            "label": "Texas", 
            "offsets": [
                {
                    "length": 5, 
                    "offset": 58
                }
            ], 
            "types": [
                {
                    "label": "Place", 
                    "uri": "http://dbpedia.org/ontology/Place"
                }, 
                {
                    "label": "Resource", 
                    "uri": "http://www.w3.org/2000/01/rdf-schema#Resource"
                }, 
                {
                    "label": "States Of The Confederate States Of America", 
                    "uri": "http://dbpedia.org/class/yago/StatesOfTheConfederateStatesOfAmerica"
                }, 
                {
                    "label": "Yago Geo Entity", 
                    "uri": "http://dbpedia.org/class/yago/YagoGeoEntity"
                }, 
                {
                    "label": "States And Territories Established In1845", 
                    "uri": "http://dbpedia.org/class/yago/StatesAndTerritoriesEstablishedIn1845"
                }, 
                {
                    "label": "Class", 
                    "uri": "http://www.w3.org/2002/07/owl#Class"
                }, 
                {
                    "label": "Populated Place", 
                    "uri": "http://dbpedia.org/ontology/PopulatedPlace"
                }, 
                {
                    "label": "Thing", 
                    "uri": "http://www.w3.org/2002/07/owl#Thing"
                }, 
                {
                    "label": "nationality", 
                    "uri": "http://sw.opencyc.org/2008/06/10/concept/en/PersonTypeByNationality"
                }, 
                {
                    "label": "States Of The United States", 
                    "uri": "http://dbpedia.org/class/yago/StatesOfTheUnitedStates"
                }, 
                {
                    "label": "Locations", 
                    "uri": "http://dbpedia.org/class/yago/Locations"
                }, 
                {
                    "label": " Feature", 
                    "uri": "http://www.opengis.net/gml/_Feature"
                }, 
                {
                    "label": "Administrative Region", 
                    "uri": "http://dbpedia.org/ontology/AdministrativeRegion"
                }
            ], 
            "uri": "http://dbpedia.org/resource/Texas"
        }, 
        {
            "label": "Childress", 
            "offsets": [
                {
                    "length": 9, 
                    "offset": 103
                }
            ], 
            "types": [
                {
                    "label": "Thing", 
                    "uri": "http://www.w3.org/2002/07/owl#Thing"
                }, 
                {
                    "label": "Resource", 
                    "uri": "http://www.w3.org/2000/01/rdf-schema#Resource"
                }
            ], 
            "uri": "http://dbpedia.org/resource/Childress"
        }
    ], 
    "mainText": "He said the state had sent 23 members of the National and Texas State Guards to the areas of Amarillo, Childress, Lubbock and Pampa to help with rescue efforts.", 
    "shownText": "He said the state had sent 23 members of the National and Texas State Guards to the areas of Amarillo, Childress, Lubbock and Pampa to help with rescue efforts.", 
    "title": "Strong Storm in Plains Brings Added Hazards - NYTimes.com"
}