{
  "mainText":"In The Washington Post on Wednesday, the columnist Courtland Milloy went on a full-frontal attack of both the first lady\u2019s agenda and the attention to her appearance, which he implied she had invited.\n\u201cEnough with the broccoli and Brussels sprouts,\u201d he wrote, \u201cto say nothing about all the attention paid to her arms, hair, derrière and designer clothes.\nWhere is that intellectually gifted Princeton graduate, the Harvard-educated lawyer and mentor to the man who would become the first African-American president of the United States?\u201d",
  "shownText":"Recently, Mrs. Obama has come under increased scrutiny after flying largely under the radar since the end of the 2012 presidential campaign.\nOn Sunday, she announced the winner of the best picture award at the Oscars via satellite from the White House, which caused a minor national kerfuffle as some pondered the propriety of her appearance.\n\nIn The Washington Post on Wednesday, the columnist Courtland Milloy went on a full-frontal attack of both the first lady\u2019s agenda and the attention to her appearance, which he implied she had invited.\n\u201cEnough with the broccoli and Brussels sprouts,\u201d he wrote, \u201cto say nothing about all the attention paid to her arms, hair, derrière and designer clothes.\nWhere is that intellectually gifted Princeton graduate, the Harvard-educated lawyer and mentor to the man who would become the first African-American president of the United States?\u201d\n\nHer dancing with middle school students, doing push-ups on \u201cThe Ellen DeGeneres Show,\u201d running out for tapas with her girlfriends and clipping her locks into modern bangs both thrill and deeply annoy a nation that projects much onto its first ladies.\n",
  "title":"New Attention to First Lady - NYTimes.com",
  "articleUrl":"http://www.nytimes.com/2013/02/28/us/politics/new-attention-to-first-lady.html?ref=health",
  "category":"health",
  "docID":"P3-0098",
  "elementNumber":14,
  "mainEntities":[
    {
      "uri":"http://dbpedia.org/resource/United_States",
      "label":"United States",
      "offsets":[
        {
          "offset":866,
          "length":13
        }
      ],
      "types":[
        {
          "label":"certain distant countries with interests in the hormuz area hormuz area topic",
          "uri":"http://sw.opencyc.org/concept/Mx4r8gRhpGJsQdiL9-7bzdhMug"
        },
        {
          "label":"representative democracy",
          "uri":"http://sw.opencyc.org/concept/Mx4rUIPoAG28EdaAAACgyZzFrg"
        },
        {
          "label":"Place",
          "uri":"http://dbpedia.org/ontology/Place"
        },
        {
          "label":"Constitutional Republic",
          "uri":"http://umbel.org/umbel/sc/ConstitutionalRepublic"
        },
        {
          "label":"Representative democracy",
          "uri":"http://dbpedia.org/resource/Representative_democracy"
        },
        {
          "label":"legal agent",
          "uri":"http://sw.opencyc.org/concept/Mx4rvVinsZwpEbGdrcN5Y29ycA"
        },
        {
          "label":"Geopolitical Entity",
          "uri":"http://umbel.org/umbel/sc/GeopoliticalEntity"
        },
        {
          "label":"Constitutional republic",
          "uri":"http://dbpedia.org/resource/Constitutional_republic"
        },
        {
          "label":"the intelligence analyst reasoning domain",
          "uri":"http://sw.opencyc.org/concept/Mx4r46fYpnaNEduAAAACs6hbjw"
        },
        {
          "label":"Industrialized Country",
          "uri":"http://umbel.org/umbel/sc/IndustrializedCountry"
        },
        {
          "label":"Record Label",
          "uri":"http://dbpedia.org/ontology/RecordLabel"
        },
        {
          "label":"Former British colonies",
          "uri":"http://dbpedia.org/resource/Former_British_colonies"
        },
        {
          "label":"Country",
          "uri":"http://dbpedia.org/ontology/Country"
        },
        {
          "label":"Developed country",
          "uri":"http://dbpedia.org/resource/Developed_country"
        },
        {
          "label":"representative democracy",
          "uri":"http://sw.cyc.com/concept/Mx4rUIPoAG28EdaAAACgyZzFrg"
        },
        {
          "label":"independent country",
          "uri":"http://sw.opencyc.org/concept/Mx4rvVjk55wpEbGdrcN5Y29ycA"
        },
        {
          "label":"Liberal Democracies",
          "uri":"http://dbpedia.org/class/yago/LiberalDemocracies"
        },
        {
          "label":"Western country",
          "uri":"http://sw.opencyc.org/concept/Mx4rvXKxx5wpEbGdrcN5Y29ycA"
        },
        {
          "label":"unnatural thing",
          "uri":"http://sw.opencyc.org/concept/Mx4rvYNNKZwpEbGdrcN5Y29ycA"
        },
        {
          "label":"Superpower",
          "uri":"http://umbel.org/umbel/sc/Superpower"
        },
        {
          "label":"country",
          "uri":"http://sw.opencyc.org/concept/Mx4rvViIeZwpEbGdrcN5Y29ycA"
        },
        {
          "label":"English-speaking countries and territories",
          "uri":"http://dbpedia.org/resource/English-speaking_countries_and_territories"
        },
        {
          "label":"Populated Place",
          "uri":"http://dbpedia.org/ontology/PopulatedPlace"
        },
        {
          "label":"democratic government",
          "uri":"http://sw.opencyc.org/concept/Mx4rmR0ddG2kEdaAAACgyZzFrg"
        },
        {
          "label":"G8Nations",
          "uri":"http://dbpedia.org/class/yago/G8Nations"
        },
        {
          "label":"ns#Target",
          "uri":"http://s.zemanta.com/ns#Target"
        },
        {
          "label":"Representative Democracy",
          "uri":"http://umbel.org/umbel/sc/RepresentativeDemocracy"
        },
        {
          "label":"OECDMember Economies",
          "uri":"http://dbpedia.org/class/yago/OECDMemberEconomies"
        },
        {
          "label":"political entity",
          "uri":"http://sw.opencyc.org/concept/Mx4rvVjl2pwpEbGdrcN5Y29ycA"
        },
        {
          "label":"constitutional republic",
          "uri":"http://sw.opencyc.org/concept/Mx4rc17uPG2kEdaAAACgyZzFrg"
        },
        {
          "label":"Thing",
          "uri":"http://dbpedia.org/about/html/http://www.w3.org/2002/07/owl%01Thing"
        },
        {
          "label":"certain distant countries with interests in the hormuz area hormuz area topic",
          "uri":"http://sw.cyc.com/concept/Mx4r8gRhpGJsQdiL9-7bzdhMug"
        },
        {
          "label":"Settlement",
          "uri":"http://dbpedia.org/ontology/Settlement"
        },
        {
          "label":"constitutional republic",
          "uri":"http://sw.cyc.com/concept/Mx4rc17uPG2kEdaAAACgyZzFrg"
        },
        {
          "label":"geographical agent",
          "uri":"http://sw.opencyc.org/concept/Mx4rwTccApwpEbGdrcN5Y29ycA"
        },
        {
          "label":"united states geography topic",
          "uri":"http://sw.opencyc.org/concept/Mx4r6ORLIGJsQdiWWtw-hTd1kw"
        },
        {
          "label":"Former British Colonies",
          "uri":"http://dbpedia.org/class/yago/FormerBritishColonies"
        },
        {
          "label":"hormuz area topic",
          "uri":"http://sw.opencyc.org/concept/Mx4rxqm_NmJsQdibq8_dqUp19w"
        },
        {
          "label":"geopolitical entity or region",
          "uri":"http://sw.opencyc.org/concept/Mx4rXZR1qEdYEduAAAACs2IKfQ"
        },
        {
          "label":"political entity",
          "uri":"http://sw.cyc.com/concept/Mx4rvVjl2pwpEbGdrcN5Y29ycA"
        },
        {
          "label":"world power",
          "uri":"http://sw.opencyc.org/concept/Mx4rvaJ7ipwpEbGdrcN5Y29ycA"
        },
        {
          "label":"organization",
          "uri":"http://sw.opencyc.org/concept/Mx4rvVjVT5wpEbGdrcN5Y29ycA"
        },
        {
          "label":" Feature",
          "uri":"http://www.opengis.net/gml/_Feature"
        },
        {
          "label":"Resource",
          "uri":"http://www.w3.org/2000/01/rdf-schema#Resource"
        },
        {
          "label":"North American country",
          "uri":"http://sw.cyc.com/concept/Mx4r4qVlEJhnQdidKY2g0ysmcA"
        },
        {
          "label":"republic",
          "uri":"http://sw.opencyc.org/concept/Mx4rRh4l5m29EdaAAACgyZzFrg"
        },
        {
          "label":"industrialized country",
          "uri":"http://sw.cyc.com/concept/Mx4rwNJMLpwpEbGdrcN5Y29ycA"
        },
        {
          "label":"industrialized country",
          "uri":"http://sw.opencyc.org/concept/Mx4rwNJMLpwpEbGdrcN5Y29ycA"
        },
        {
          "label":"geopolitical entity or region",
          "uri":"http://sw.opencyc.org/concept/Mx8Ngh4rvrhK-JwpEbGdrcN5Y29ycA2DHiu9WOR2nCkRsZ2tw3ljb3JwHiu9WIAJnCkRsZ2tw3ljb3JwHiu9WOXanCkRsZ2tw3ljb3Jw"
        },
        {
          "label":"North American country",
          "uri":"http://sw.opencyc.org/concept/Mx4r4qVlEJhnQdidKY2g0ysmcA"
        },
        {
          "label":"world power",
          "uri":"http://sw.cyc.com/concept/Mx4rvaJ7ipwpEbGdrcN5Y29ycA"
        },
        {
          "label":"federal republic",
          "uri":"http://sw.opencyc.org/concept/Mx4rv02eLm2kEdaAAACgyZzFrg"
        },
        {
          "label":"Thing",
          "uri":"http://www.w3.org/2002/07/owl#Thing"
        },
        {
          "label":"Spatial Thing",
          "uri":"http://www.w3.org/2003/01/geo/wgs84_pos#SpatialThing"
        },
        {
          "label":"Superpower",
          "uri":"http://dbpedia.org/resource/Superpower"
        },
        {
          "label":"WTOMember Economies",
          "uri":"http://dbpedia.org/class/yago/WTOMemberEconomies"
        },
        {
          "label":"North American Country",
          "uri":"http://umbel.org/umbel/sc/NorthAmericanCountry"
        }
      ]
    },
    {
      "uri":"http://dbpedia.org/resource/Brussels",
      "label":"Brussels",
      "offsets":[
        {
          "offset":575,
          "length":8
        }
      ],
      "types":[
        {
          "label":"Place",
          "uri":"http://dbpedia.org/ontology/Place"
        },
        {
          "label":"Resource",
          "uri":"http://www.w3.org/2000/01/rdf-schema#Resource"
        },
        {
          "label":"capital",
          "uri":"http://sw.opencyc.org/2008/06/10/concept/Mx4rvVjylZwpEbGdrcN5Y29ycA"
        },
        {
          "label":"Capitals In Europe",
          "uri":"http://dbpedia.org/class/yago/CapitalsInEurope"
        },
        {
          "label":"European Capitals Of Culture",
          "uri":"http://dbpedia.org/class/yago/EuropeanCapitalsOfCulture"
        },
        {
          "label":"Populated Place",
          "uri":"http://dbpedia.org/ontology/PopulatedPlace"
        },
        {
          "label":"Regions Of Belgium",
          "uri":"http://dbpedia.org/class/yago/RegionsOfBelgium"
        },
        {
          "label":"Regions Of Europe With Multiple Official Languages",
          "uri":"http://dbpedia.org/class/yago/RegionsOfEuropeWithMultipleOfficialLanguages"
        },
        {
          "label":"Thing",
          "uri":"http://www.w3.org/2002/07/owl#Thing"
        },
        {
          "label":"first order administrative division",
          "uri":"http://sw.opencyc.org/2008/06/10/concept/Mx4r6Ki-3KMNEdqAAAACs6hO_g"
        },
        {
          "label":"NUTS1Statistical Regions Of The European Union",
          "uri":"http://dbpedia.org/class/yago/NUTS1StatisticalRegionsOfTheEuropeanUnion"
        },
        {
          "label":"City",
          "uri":"http://dbpedia.org/class/yago/City108524735"
        },
        {
          "label":"Geoclass Capital Of APolitical Entity",
          "uri":"http://dbpedia.org/class/yago/GeoclassCapitalOfAPoliticalEntity"
        },
        {
          "label":"Settlement",
          "uri":"http://dbpedia.org/ontology/Settlement"
        },
        {
          "label":" Feature",
          "uri":"http://www.opengis.net/gml/_Feature"
        }
      ]
    }
  ],
  "allEntities":[
    {
      "uri":"http://dbpedia.org/resource/United_States",
      "label":"United States",
      "offsets":[
        {
          "offset":866,
          "length":13
        }
      ],
      "types":[
        {
          "label":"certain distant countries with interests in the hormuz area hormuz area topic",
          "uri":"http://sw.opencyc.org/concept/Mx4r8gRhpGJsQdiL9-7bzdhMug"
        },
        {
          "label":"representative democracy",
          "uri":"http://sw.opencyc.org/concept/Mx4rUIPoAG28EdaAAACgyZzFrg"
        },
        {
          "label":"Place",
          "uri":"http://dbpedia.org/ontology/Place"
        },
        {
          "label":"Constitutional Republic",
          "uri":"http://umbel.org/umbel/sc/ConstitutionalRepublic"
        },
        {
          "label":"Representative democracy",
          "uri":"http://dbpedia.org/resource/Representative_democracy"
        },
        {
          "label":"legal agent",
          "uri":"http://sw.opencyc.org/concept/Mx4rvVinsZwpEbGdrcN5Y29ycA"
        },
        {
          "label":"Geopolitical Entity",
          "uri":"http://umbel.org/umbel/sc/GeopoliticalEntity"
        },
        {
          "label":"Constitutional republic",
          "uri":"http://dbpedia.org/resource/Constitutional_republic"
        },
        {
          "label":"the intelligence analyst reasoning domain",
          "uri":"http://sw.opencyc.org/concept/Mx4r46fYpnaNEduAAAACs6hbjw"
        },
        {
          "label":"Industrialized Country",
          "uri":"http://umbel.org/umbel/sc/IndustrializedCountry"
        },
        {
          "label":"Record Label",
          "uri":"http://dbpedia.org/ontology/RecordLabel"
        },
        {
          "label":"Former British colonies",
          "uri":"http://dbpedia.org/resource/Former_British_colonies"
        },
        {
          "label":"Country",
          "uri":"http://dbpedia.org/ontology/Country"
        },
        {
          "label":"Developed country",
          "uri":"http://dbpedia.org/resource/Developed_country"
        },
        {
          "label":"representative democracy",
          "uri":"http://sw.cyc.com/concept/Mx4rUIPoAG28EdaAAACgyZzFrg"
        },
        {
          "label":"independent country",
          "uri":"http://sw.opencyc.org/concept/Mx4rvVjk55wpEbGdrcN5Y29ycA"
        },
        {
          "label":"Liberal Democracies",
          "uri":"http://dbpedia.org/class/yago/LiberalDemocracies"
        },
        {
          "label":"Western country",
          "uri":"http://sw.opencyc.org/concept/Mx4rvXKxx5wpEbGdrcN5Y29ycA"
        },
        {
          "label":"unnatural thing",
          "uri":"http://sw.opencyc.org/concept/Mx4rvYNNKZwpEbGdrcN5Y29ycA"
        },
        {
          "label":"Superpower",
          "uri":"http://umbel.org/umbel/sc/Superpower"
        },
        {
          "label":"country",
          "uri":"http://sw.opencyc.org/concept/Mx4rvViIeZwpEbGdrcN5Y29ycA"
        },
        {
          "label":"English-speaking countries and territories",
          "uri":"http://dbpedia.org/resource/English-speaking_countries_and_territories"
        },
        {
          "label":"Populated Place",
          "uri":"http://dbpedia.org/ontology/PopulatedPlace"
        },
        {
          "label":"democratic government",
          "uri":"http://sw.opencyc.org/concept/Mx4rmR0ddG2kEdaAAACgyZzFrg"
        },
        {
          "label":"G8Nations",
          "uri":"http://dbpedia.org/class/yago/G8Nations"
        },
        {
          "label":"ns#Target",
          "uri":"http://s.zemanta.com/ns#Target"
        },
        {
          "label":"Representative Democracy",
          "uri":"http://umbel.org/umbel/sc/RepresentativeDemocracy"
        },
        {
          "label":"OECDMember Economies",
          "uri":"http://dbpedia.org/class/yago/OECDMemberEconomies"
        },
        {
          "label":"political entity",
          "uri":"http://sw.opencyc.org/concept/Mx4rvVjl2pwpEbGdrcN5Y29ycA"
        },
        {
          "label":"constitutional republic",
          "uri":"http://sw.opencyc.org/concept/Mx4rc17uPG2kEdaAAACgyZzFrg"
        },
        {
          "label":"Thing",
          "uri":"http://dbpedia.org/about/html/http://www.w3.org/2002/07/owl%01Thing"
        },
        {
          "label":"certain distant countries with interests in the hormuz area hormuz area topic",
          "uri":"http://sw.cyc.com/concept/Mx4r8gRhpGJsQdiL9-7bzdhMug"
        },
        {
          "label":"Settlement",
          "uri":"http://dbpedia.org/ontology/Settlement"
        },
        {
          "label":"constitutional republic",
          "uri":"http://sw.cyc.com/concept/Mx4rc17uPG2kEdaAAACgyZzFrg"
        },
        {
          "label":"geographical agent",
          "uri":"http://sw.opencyc.org/concept/Mx4rwTccApwpEbGdrcN5Y29ycA"
        },
        {
          "label":"united states geography topic",
          "uri":"http://sw.opencyc.org/concept/Mx4r6ORLIGJsQdiWWtw-hTd1kw"
        },
        {
          "label":"Former British Colonies",
          "uri":"http://dbpedia.org/class/yago/FormerBritishColonies"
        },
        {
          "label":"hormuz area topic",
          "uri":"http://sw.opencyc.org/concept/Mx4rxqm_NmJsQdibq8_dqUp19w"
        },
        {
          "label":"geopolitical entity or region",
          "uri":"http://sw.opencyc.org/concept/Mx4rXZR1qEdYEduAAAACs2IKfQ"
        },
        {
          "label":"political entity",
          "uri":"http://sw.cyc.com/concept/Mx4rvVjl2pwpEbGdrcN5Y29ycA"
        },
        {
          "label":"world power",
          "uri":"http://sw.opencyc.org/concept/Mx4rvaJ7ipwpEbGdrcN5Y29ycA"
        },
        {
          "label":"organization",
          "uri":"http://sw.opencyc.org/concept/Mx4rvVjVT5wpEbGdrcN5Y29ycA"
        },
        {
          "label":" Feature",
          "uri":"http://www.opengis.net/gml/_Feature"
        },
        {
          "label":"Resource",
          "uri":"http://www.w3.org/2000/01/rdf-schema#Resource"
        },
        {
          "label":"North American country",
          "uri":"http://sw.cyc.com/concept/Mx4r4qVlEJhnQdidKY2g0ysmcA"
        },
        {
          "label":"republic",
          "uri":"http://sw.opencyc.org/concept/Mx4rRh4l5m29EdaAAACgyZzFrg"
        },
        {
          "label":"industrialized country",
          "uri":"http://sw.cyc.com/concept/Mx4rwNJMLpwpEbGdrcN5Y29ycA"
        },
        {
          "label":"industrialized country",
          "uri":"http://sw.opencyc.org/concept/Mx4rwNJMLpwpEbGdrcN5Y29ycA"
        },
        {
          "label":"geopolitical entity or region",
          "uri":"http://sw.opencyc.org/concept/Mx8Ngh4rvrhK-JwpEbGdrcN5Y29ycA2DHiu9WOR2nCkRsZ2tw3ljb3JwHiu9WIAJnCkRsZ2tw3ljb3JwHiu9WOXanCkRsZ2tw3ljb3Jw"
        },
        {
          "label":"North American country",
          "uri":"http://sw.opencyc.org/concept/Mx4r4qVlEJhnQdidKY2g0ysmcA"
        },
        {
          "label":"world power",
          "uri":"http://sw.cyc.com/concept/Mx4rvaJ7ipwpEbGdrcN5Y29ycA"
        },
        {
          "label":"federal republic",
          "uri":"http://sw.opencyc.org/concept/Mx4rv02eLm2kEdaAAACgyZzFrg"
        },
        {
          "label":"Thing",
          "uri":"http://www.w3.org/2002/07/owl#Thing"
        },
        {
          "label":"Spatial Thing",
          "uri":"http://www.w3.org/2003/01/geo/wgs84_pos#SpatialThing"
        },
        {
          "label":"Superpower",
          "uri":"http://dbpedia.org/resource/Superpower"
        },
        {
          "label":"WTOMember Economies",
          "uri":"http://dbpedia.org/class/yago/WTOMemberEconomies"
        },
        {
          "label":"North American Country",
          "uri":"http://umbel.org/umbel/sc/NorthAmericanCountry"
        }
      ]
    },
    {
      "uri":"http://dbpedia.org/resource/Brussels",
      "label":"Brussels",
      "offsets":[
        {
          "offset":575,
          "length":8
        }
      ],
      "types":[
        {
          "label":"Place",
          "uri":"http://dbpedia.org/ontology/Place"
        },
        {
          "label":"Resource",
          "uri":"http://www.w3.org/2000/01/rdf-schema#Resource"
        },
        {
          "label":"capital",
          "uri":"http://sw.opencyc.org/2008/06/10/concept/Mx4rvVjylZwpEbGdrcN5Y29ycA"
        },
        {
          "label":"Capitals In Europe",
          "uri":"http://dbpedia.org/class/yago/CapitalsInEurope"
        },
        {
          "label":"European Capitals Of Culture",
          "uri":"http://dbpedia.org/class/yago/EuropeanCapitalsOfCulture"
        },
        {
          "label":"Populated Place",
          "uri":"http://dbpedia.org/ontology/PopulatedPlace"
        },
        {
          "label":"Regions Of Belgium",
          "uri":"http://dbpedia.org/class/yago/RegionsOfBelgium"
        },
        {
          "label":"Regions Of Europe With Multiple Official Languages",
          "uri":"http://dbpedia.org/class/yago/RegionsOfEuropeWithMultipleOfficialLanguages"
        },
        {
          "label":"Thing",
          "uri":"http://www.w3.org/2002/07/owl#Thing"
        },
        {
          "label":"first order administrative division",
          "uri":"http://sw.opencyc.org/2008/06/10/concept/Mx4r6Ki-3KMNEdqAAAACs6hO_g"
        },
        {
          "label":"NUTS1Statistical Regions Of The European Union",
          "uri":"http://dbpedia.org/class/yago/NUTS1StatisticalRegionsOfTheEuropeanUnion"
        },
        {
          "label":"City",
          "uri":"http://dbpedia.org/class/yago/City108524735"
        },
        {
          "label":"Geoclass Capital Of APolitical Entity",
          "uri":"http://dbpedia.org/class/yago/GeoclassCapitalOfAPoliticalEntity"
        },
        {
          "label":"Settlement",
          "uri":"http://dbpedia.org/ontology/Settlement"
        },
        {
          "label":" Feature",
          "uri":"http://www.opengis.net/gml/_Feature"
        }
      ]
    },
    {
      "uri":"http://dbpedia.org/resource/White_House",
      "label":"White House",
      "offsets":[
        {
          "offset":240,
          "length":11
        }
      ],
      "types":[
        {
          "label":"Buildings Of The United States Government In Washington,D.C.",
          "uri":"http://dbpedia.org/class/yago/BuildingsOfTheUnitedStatesGovernmentInWashington,D.C."
        },
        {
          "label":"Presidential Palaces",
          "uri":"http://dbpedia.org/class/yago/PresidentialPalaces"
        },
        {
          "label":"Thing",
          "uri":"http://www.w3.org/2002/07/owl#Thing"
        },
        {
          "label":"Rebuilt Buildings And Structures",
          "uri":"http://dbpedia.org/class/yago/RebuiltBuildingsAndStructures"
        },
        {
          "label":"Place",
          "uri":"http://dbpedia.org/ontology/Place"
        },
        {
          "label":"executive branch of government",
          "uri":"http://sw.opencyc.org/2008/06/10/concept/Mx4rZfkIHrThQdiWL_Y3RJ_NSA"
        },
        {
          "label":"government organizations organization topic",
          "uri":"http://sw.opencyc.org/2008/06/10/concept/Mx4r8sgDFmJsQdiZTqJodntKpA"
        },
        {
          "label":"19th century architecture",
          "uri":"http://dbpedia.org/resource/19th_century_architecture"
        },
        {
          "label":"Building",
          "uri":"http://dbpedia.org/class/yago/Building102913152"
        },
        {
          "label":"Building",
          "uri":"http://dbpedia.org/ontology/Building"
        },
        {
          "label":"branch of U.S. Government",
          "uri":"http://sw.opencyc.org/2008/06/10/concept/Mx4rTo_pVPbDEdyAAAACs6hRXg"
        },
        {
          "label":"19th century works",
          "uri":"http://dbpedia.org/resource/19th_century_works"
        }
      ]
    }
  ]
}